ParallelAtariBreakoutEnv/ParallelAtariEnv.py
ParallelAtariBreakoutEnv/__init__.py
ParallelAtariBreakoutEnv-0.0.4.0.dist-info/METADATA
ParallelAtariBreakoutEnv-0.0.4.0.dist-info/WHEEL
ParallelAtariBreakoutEnv-0.0.4.0.dist-info/top_level.txt
ParallelAtariBreakoutEnv-0.0.4.0.dist-info/RECORD
